xmodem/__init__.py
xmodem/__main__.py
xmodem-0.4.7.data/data/doc/XMODEM.TXT
xmodem-0.4.7.data/data/doc/XMODEM1K.TXT
xmodem-0.4.7.data/data/doc/XMODMCRC.TXT
xmodem-0.4.7.data/data/doc/ymodem.txt
xmodem-0.4.7.dist-info/LICENSE
xmodem-0.4.7.dist-info/METADATA
xmodem-0.4.7.dist-info/WHEEL
xmodem-0.4.7.dist-info/top_level.txt
xmodem-0.4.7.dist-info/RECORD
