Metadata-Version: 2.1
Name: xmodem
Version: 0.4.7
Summary: XMODEM protocol implementation.
Home-page: https://github.com/tehmaze/xmodem
Author: Wijnand Modderman, Jeff Quast, Kris Hardy
Author-email: maze@pyth0n.org
License: MIT
Keywords: xmodem protocol
License-File: LICENSE
